obsutils/__init__.py
obsutils/file.py
obsutils-1.0.8.dist-info/METADATA
obsutils-1.0.8.dist-info/WHEEL
obsutils-1.0.8.dist-info/top_level.txt
obsutils-1.0.8.dist-info/RECORD
